README.md
setup.py
chalglm_llm.egg-info/PKG-INFO
chalglm_llm.egg-info/SOURCES.txt
chalglm_llm.egg-info/dependency_links.txt
chalglm_llm.egg-info/entry_points.txt
chalglm_llm.egg-info/not-zip-safe
chalglm_llm.egg-info/requires.txt
chalglm_llm.egg-info/top_level.txt
chatglm_src/__init__.py
chatglm_src/callbacks.py
chatglm_src/cmd.py
chatglm_src/llm.py