Metadata-Version: 2.1
Name: chalglm-llm
Version: 0.0.0
Summary: chatglm llm
Home-page: https://github.com/xxx
Author: auth
Author-email: xxx@gmail.com
License: MIT
